setup.py
HQChartPy2/HQChartPy2.pyd
HQChartPy2/HQChartPy2.so
HQChartPy2/__init__.py
HQChartPy2/libcrypto-1_1-x64.dll
HQChartPy2/libssl-1_1-x64.dll
HQChartPy2/pkg_info.json
HQChartPy2.egg-info/PKG-INFO
HQChartPy2.egg-info/SOURCES.txt
HQChartPy2.egg-info/dependency_links.txt
HQChartPy2.egg-info/top_level.txt
hqchartPy2.egg-info/PKG-INFO
hqchartPy2.egg-info/SOURCES.txt
hqchartPy2.egg-info/dependency_links.txt
hqchartPy2.egg-info/top_level.txt